morty_portal_gun/__init__.py
morty_portal_gun/database.py
morty_portal_gun/main.py
morty_portal_gun/utilities.py
morty_portal_gun-1.0.1.dist-info/METADATA
morty_portal_gun-1.0.1.dist-info/entry_points.txt
morty_portal_gun-1.0.1.dist-info/WHEEL
morty_portal_gun-1.0.1.dist-info/RECORD
