Metadata-Version: 2.1
Name: morty-portal-gun
Version: 1.0.1
Summary: 
Author: test-python-wheel
Author-email: test-python-wheel-project@outlook.com
Requires-Python: >=3.8,<4.0
Classifier: Programming Language :: Python :: 3
Classifier: Programming Language :: Python :: 3.8
Classifier: Programming Language :: Python :: 3.9
Classifier: Programming Language :: Python :: 3.10
Classifier: Programming Language :: Python :: 3.11
Requires-Dist: tinydb (>=4.7.1,<5.0.0)
Requires-Dist: typer[all] (>=0.7.0,<0.8.0)
